iphack/__init__.py
iphack/iphack.py
iphack-1.0.4.dist-info/WHEEL
iphack-1.0.4.dist-info/METADATA
iphack-1.0.4.dist-info/RECORD
