Metadata-Version: 2.1
Name: iphack
Version: 1.0.4
Summary: the most ideal tool for finding out information about IP: github.com/mishakorzik/IpHack
License: Apache-2.0
Author: MishaKorzhik_He1Zen
Author-email: miguardzecurity@gmail.com
Requires-Python: >=3.6,<4.0
Classifier: License :: OSI Approved :: Apache Software License
Classifier: Programming Language :: Python :: 3
Classifier: Programming Language :: Python :: 3.10
Classifier: Programming Language :: Python :: 3.6
Classifier: Programming Language :: Python :: 3.7
Classifier: Programming Language :: Python :: 3.8
Classifier: Programming Language :: Python :: 3.9
